spici/__init__.py
spici-0.1.0.dist-info/LICENSE.txt
spici-0.1.0.dist-info/METADATA
spici-0.1.0.dist-info/WHEEL
spici-0.1.0.dist-info/top_level.txt
spici-0.1.0.dist-info/RECORD
