Metadata-Version: 2.1
Name: spici
Version: 0.1.0
Summary: spice your data
Home-page: 
Author: Eklavya Gupta
Author-email: emessage.eg@gmail.com
License: MIT
Keywords: data prepration
Classifier: Development Status :: 5 - Production/Stable
Classifier: Intended Audience :: Science/Research
Classifier: Operating System :: Microsoft :: Windows :: Windows 11
Classifier: License :: OSI Approved :: MIT License
Classifier: Programming Language :: Python :: 3.11
License-File: LICENSE.txt
Requires-Dist: pandas
Requires-Dist: numpy
Requires-Dist: seaborn
Requires-Dist: matplotlib
